idpauth/__init__.py
idpauth/idp_authentication.py
idpauth/idp_authorization.py
idpauth-1.0.2.dist-info/METADATA
idpauth-1.0.2.dist-info/WHEEL
idpauth-1.0.2.dist-info/top_level.txt
idpauth-1.0.2.dist-info/RECORD
