Metadata-Version: 2.1
Name: idpauth
Version: 1.0.2
Summary: CAS Authenticator: An Authenticator for Jupyterhub that authenticates against an external CAS service.
Home-page: https://github.com/yaya/idpauth
Author: Carl (https://github.com/cwaldbieser)
Author-email: UNKNOWN
License: GPLv3
Keywords: Interactive,Interpreter,Shell,Web
Platform: Linux
Platform: Mac OS X
Classifier: Intended Audience :: Developers
Classifier: Intended Audience :: System Administrators
Classifier: Intended Audience :: Science/Research
Classifier: License :: OSI Approved :: GNU General Public License v3 (GPLv3)
Classifier: Programming Language :: Python
Classifier: Programming Language :: Python :: 3
Requires-Dist: jupyterhub
Requires-Dist: lxml
